sporc/__init__.py
sporc/cli.py
sporc/constants.py
sporc/dataset.py
sporc/episode.py
sporc/exceptions.py
sporc/podcast.py
sporc/turn.py
sporc-0.1.7.dist-info/LICENSE
sporc-0.1.7.dist-info/METADATA
sporc-0.1.7.dist-info/WHEEL
sporc-0.1.7.dist-info/entry_points.txt
sporc-0.1.7.dist-info/top_level.txt
sporc-0.1.7.dist-info/RECORD
