Metadata-Version: 2.1
Name: sporc
Version: 0.1.7
Summary: A Python package for working with the SPORC (Structured Podcast Open Research Corpus) dataset
Home-page: https://github.com/yourusername/sporc
Author: SPORC Package Maintainer
Author-email: David Jurgens <jurgens@umich.edu>
Maintainer-email: David Jurgens <jurgens@umich.edu>
License: MIT
Project-URL: Homepage, https://github.com/davidjurgens/sporc
Project-URL: Documentation, https://github.com/davidjurgens/sporc/wiki
Project-URL: Repository, https://github.com/davidjurgens/sporc.git
Project-URL: Bug Tracker, https://github.com/davidjurgens/sporc/issues
Project-URL: Source Code, https://github.com/davidjurgens/sporc
Project-URL: Dataset, https://huggingface.co/datasets/blitt/SPoRC
Keywords: podcast,dataset,nlp,conversation,speech,transcript,huggingface
Classifier: Development Status :: 4 - Beta
Classifier: Intended Audience :: Science/Research
Classifier: Intended Audience :: Developers
Classifier: License :: OSI Approved :: MIT License
Classifier: Operating System :: OS Independent
Classifier: Programming Language :: Python :: 3
Classifier: Programming Language :: Python :: 3.8
Classifier: Programming Language :: Python :: 3.9
Classifier: Programming Language :: Python :: 3.10
Classifier: Programming Language :: Python :: 3.11
Classifier: Programming Language :: Python :: 3.12
Classifier: Topic :: Scientific/Engineering :: Artificial Intelligence
Classifier: Topic :: Scientific/Engineering :: Information Analysis
Classifier: Topic :: Text Processing :: Linguistic
Classifier: Topic :: Multimedia :: Sound/Audio :: Speech
Requires-Python: >=3.8
License-File: LICENSE
Requires-Dist: datasets >=2.0.0
Requires-Dist: huggingface-hub >=0.16.0
Requires-Dist: psutil >=5.8.0
Provides-Extra: dev
Requires-Dist: pytest >=7.0.0 ; extra == 'dev'
Requires-Dist: pytest-cov >=4.0.0 ; extra == 'dev'
Requires-Dist: black >=22.0.0 ; extra == 'dev'
Requires-Dist: isort >=5.0.0 ; extra == 'dev'
Requires-Dist: flake8 >=5.0.0 ; extra == 'dev'
Requires-Dist: mypy >=1.0.0 ; extra == 'dev'
Requires-Dist: pre-commit >=2.20.0 ; extra == 'dev'
Provides-Extra: docs
Requires-Dist: sphinx >=5.0.0 ; extra == 'docs'
Requires-Dist: sphinx-rtd-theme >=1.0.0 ; extra == 'docs'
Requires-Dist: myst-parser >=0.18.0 ; extra == 'docs'
Provides-Extra: streaming
Requires-Dist: psutil >=5.8.0 ; extra == 'streaming'
Provides-Extra: test
Requires-Dist: pytest >=7.0.0 ; extra == 'test'
Requires-Dist: pytest-cov >=4.0.0 ; extra == 'test'
Requires-Dist: pytest-mock >=3.8.0 ; extra == 'test'
